zadachi_shest.py
zadachi_shest-1.0.1.dist-info/WHEEL
zadachi_shest-1.0.1.dist-info/METADATA
zadachi_shest-1.0.1.dist-info/RECORD
