Metadata-Version: 2.1
Name: zadachi-shest
Version: 1.0.1
Summary: rabotay suka
Author: NuatStanskiy
Author-email: smiril13@mail.ru
Requires-Python: >=3.10,<4.0
Classifier: Programming Language :: Python :: 3
Classifier: Programming Language :: Python :: 3.10
